{"pairKey":"chael-sonnen--rashad-evans","fighters":["Chael Sonnen","Rashad Evans"],"slugs":["chael-sonnen","rashad-evans"],"verdictRule":"The higher totalScore is the UFC-only GOAT comparison winner. Real head-to-head results are context only.","verdictStatus":"decided-by-totalScore","verdictWinner":"Rashad Evans","verdictLoser":"Chael Sonnen","winnerScore":44.95,"loserScore":23.58,"winnerRank":48,"loserRank":60,"margin":21.37,"headToHead":{"seriesWinner":"Rashad Evans","fights":1,"importance":"notable","summary":"Rashad stopped Chael late in Chael’s UFC run, treated as a post-prime/exit result.","contextOnly":true,"doesNotOverrideVerdict":true}}
