{"pairKey":"jose-aldo--max-holloway","fighters":["Jose Aldo","Max Holloway"],"slugs":["jose-aldo","max-holloway"],"verdictRule":"The higher totalScore is the comparison winner. Head-to-head results are context only and never override this verdict.","verdictStatus":"decided-by-totalScore","verdictWinner":"Jose Aldo","verdictLoser":"Max Holloway","winnerScore":62.29,"loserScore":55.74,"winnerRank":8,"loserRank":15,"margin":6.55,"headToHead":{"seriesWinner":"Max Holloway","fights":2,"importance":"major","summary":"Holloway finished Aldo twice in featherweight title fights, which gives Max clear separation even though Aldo's broader historical legacy remains massive.","contextOnly":true,"doesNotOverrideVerdict":true}}
