{"pairKey":"robbie-lawler--tyron-woodley","fighters":["Robbie Lawler","Tyron Woodley"],"slugs":["robbie-lawler","tyron-woodley"],"verdictRule":"The higher totalScore is the UFC-only GOAT comparison winner. Real head-to-head results are context only.","verdictStatus":"decided-by-totalScore","verdictWinner":"Tyron Woodley","verdictLoser":"Robbie Lawler","winnerScore":48.49,"loserScore":47.29,"winnerRank":28,"loserRank":35,"margin":1.2,"headToHead":{"seriesWinner":"Tyron Woodley","fights":1,"importance":"major","summary":"Woodley knocked out Lawler to win the welterweight title and end Robbie’s reign.","contextOnly":true,"doesNotOverrideVerdict":true}}
